pomodoropie/__init__.py
pomodoropie/__main__.py
pomodoropie/session.py
Pomodoropie-1.0.3.dist-info/LICENSE.txt
Pomodoropie-1.0.3.dist-info/METADATA
Pomodoropie-1.0.3.dist-info/WHEEL
Pomodoropie-1.0.3.dist-info/entry_points.txt
Pomodoropie-1.0.3.dist-info/top_level.txt
Pomodoropie-1.0.3.dist-info/RECORD
