Metadata-Version: 2.1
Name: Pomodoropie
Version: 1.0.3
Summary: A Python pomodoro clock
Home-page: https://github.com/Jeff-Moorhead/pomodoropie
Author: Jeff Moorhead
Author-email: jeff.moorhead1@gmail.com
License: UNKNOWN
Platform: UNKNOWN
